LICENSE
MANIFEST.in
README.md
setup.cfg
setup.py
djangoplus_enderecos.egg-info/PKG-INFO
djangoplus_enderecos.egg-info/SOURCES.txt
djangoplus_enderecos.egg-info/dependency_links.txt
djangoplus_enderecos.egg-info/top_level.txt
enderecos/__init__.py
enderecos/models.py
enderecos/views.py
enderecos/db/__init__.py
enderecos/db/fields.py
enderecos/fixtures/.DS_Store
enderecos/fixtures/cidades.json.zip
enderecos/fixtures/initial_data.json.zip
enderecos/fixtures/test.json
enderecos/forms/__init__.py
enderecos/forms/fields.py
enderecos/forms/widgets.py
enderecos/management/__init__.py
enderecos/management/commands/__init__.py
enderecos/management/commands/carregar_cidades.py
enderecos/migrations/0001_initial.py
enderecos/migrations/0001_squashed_0006_auto_20170605_2058.py
enderecos/migrations/0002_auto_20190520_1330.py
enderecos/migrations/0002_initial.py
enderecos/migrations/0003_delete_telefone.py
enderecos/migrations/0004_auto_20170503_1923.py
enderecos/migrations/0005_auto_20170503_2210.py
enderecos/migrations/0006_auto_20170605_2058.py
enderecos/migrations/__init__.py
enderecos/migrations/__pycache__/0001_initial.cpython-37.pyc
enderecos/migrations/__pycache__/0001_squashed_0006_auto_20170605_2058.cpython-37.pyc
enderecos/migrations/__pycache__/0002_initial.cpython-37.pyc
enderecos/migrations/__pycache__/0003_delete_telefone.cpython-37.pyc
enderecos/migrations/__pycache__/0004_auto_20170503_1923.cpython-37.pyc
enderecos/migrations/__pycache__/0005_auto_20170503_2210.cpython-37.pyc
enderecos/migrations/__pycache__/0006_auto_20170605_2058.cpython-37.pyc
enderecos/migrations/__pycache__/__init__.cpython-37.pyc